BitBit/BitBit.py
BitBit/__init__.py
BiBit-8.1.9.dist-info/LICENSE.txt
BiBit-8.1.9.dist-info/METADATA
BiBit-8.1.9.dist-info/WHEEL
BiBit-8.1.9.dist-info/entry_points.txt
BiBit-8.1.9.dist-info/top_level.txt
BiBit-8.1.9.dist-info/RECORD
